torch_numopt/__init__.py
torch_numopt/adahessian.py
torch_numopt/conjugate_gradient.py
torch_numopt/custom_optimizer.py
torch_numopt/gauss_newton_optim.py
torch_numopt/gradient_descent_lineseach.py
torch_numopt/lbfgs_optim.py
torch_numopt/line_search_optimizer.py
torch_numopt/lm_optim.py
torch_numopt/newton_optim.py
torch_numopt/second_order_optimizer.py
torch_numopt/utils.py
torch_numopt-0.3.1.dist-info/METADATA
torch_numopt-0.3.1.dist-info/WHEEL
torch_numopt-0.3.1.dist-info/top_level.txt
torch_numopt-0.3.1.dist-info/RECORD
