Metadata-Version: 2.4
Name: torch_numopt
Version: 0.3.1
Summary: Classic numerical optimizaton methods for Pytorch neural networks
Author-email: eugenioLR <eugeniolorente0@gmail.com>
Project-URL: Homepage, https://github.com/GheodeAI/torch_numopt
Requires-Python: >=3.10
Requires-Dist: torch
Provides-Extra: dev
Requires-Dist: scikit-learn; extra == "dev"
Requires-Dist: matplotlib; extra == "dev"
Requires-Dist: numpy; extra == "dev"
Requires-Dist: sphinx>=7.1.1; extra == "dev"
Requires-Dist: sphinx_material; extra == "dev"
